appier_extras/__init__.py
appier_extras/base.py
appier_extras/parts/__init__.py
appier_extras/parts/admin/__init__.py
appier_extras/parts/admin/part.py
appier_extras/parts/admin/models/__init__.py
appier_extras/parts/admin/models/account.py
appier_extras/parts/admin/models/base.py
appier_extras/parts/admin/models/config.py
appier_extras/parts/admin/models/credential.py
appier_extras/parts/admin/models/event.py
appier_extras/parts/admin/models/locale.py
appier_extras/parts/admin/models/role.py
appier_extras/parts/admin/models/search.py
appier_extras/parts/admin/models/settings.py
appier_extras/parts/admin/models/snapshot.py
appier_extras/parts/admin/models/oauth/__init__.py
appier_extras/parts/admin/models/oauth/oauth_client.py
appier_extras/parts/admin/models/oauth/oauth_token.py
appier_extras/parts/admin/partials/__init__.py
appier_extras/parts/admin/partials/authenticable.py
appier_extras/parts/admin/social/__init__.py
appier_extras/parts/admin/social/facebook_s.py
appier_extras/parts/admin/social/github_s.py
appier_extras/parts/admin/social/google_s.py
appier_extras/parts/admin/social/live_s.py
appier_extras/parts/admin/social/twitter_s.py
appier_extras/parts/admin/static/css/layout.css
appier_extras/parts/admin/static/images/avatar.png
appier_extras/parts/admin/static/images/favicon.ico
appier_extras/parts/admin/static/images/logo_96.png
appier_extras/parts/admin/static/js/main.js
appier_extras/parts/admin/templates/admin/admin.fluid.html.tpl
appier_extras/parts/admin/templates/admin/admin.simple.html.tpl
appier_extras/parts/admin/templates/admin/admin.static.html.tpl
appier_extras/parts/admin/templates/admin/bar.html.tpl
appier_extras/parts/admin/templates/admin/content_type.html.tpl
appier_extras/parts/admin/templates/admin/doctype.html.tpl
appier_extras/parts/admin/templates/admin/end_doctype.html.tpl
appier_extras/parts/admin/templates/admin/extras.html.tpl
appier_extras/parts/admin/templates/admin/footer.html.tpl
appier_extras-0.26.6.dist-info/METADATA
appier_extras-0.26.6.dist-info/WHEEL
appier_extras-0.26.6.dist-info/entry_points.txt
appier_extras-0.26.6.dist-info/top_level.txt
appier_extras-0.26.6.dist-info/RECORD
